cortexhub/__init__.py
cortexhub/auto_protect.py
cortexhub/client.py
cortexhub/config.py
cortexhub/errors.py
cortexhub/frameworks.py
cortexhub/pipeline.py
cortexhub/version.py
cortexhub/adapters/__init__.py
cortexhub/adapters/base.py
cortexhub/adapters/claude_agents.py
cortexhub/adapters/crewai.py
cortexhub/adapters/langgraph.py
cortexhub/adapters/openai_agents.py
cortexhub/audit/__init__.py
cortexhub/audit/events.py
cortexhub/backend/__init__.py
cortexhub/backend/client.py
cortexhub/context/__init__.py
cortexhub/context/enricher.py
cortexhub/guardrails/__init__.py
cortexhub/guardrails/injection.py
cortexhub/guardrails/pii.py
cortexhub/guardrails/secrets.py
cortexhub/interceptors/__init__.py
cortexhub/interceptors/llm.py
cortexhub/interceptors/mcp.py
cortexhub/policy/__init__.py
cortexhub/policy/effects.py
cortexhub/policy/evaluator.py
cortexhub/policy/loader.py
cortexhub/policy/models.py
cortexhub/policy/sync.py
cortexhub/telemetry/__init__.py
cortexhub/telemetry/otel.py
cortexhub-0.1.8.dist-info/METADATA
cortexhub-0.1.8.dist-info/WHEEL
cortexhub-0.1.8.dist-info/licenses/LICENSE
cortexhub-0.1.8.dist-info/RECORD
