Metadata-Version: 2.4
Name: cortexhub
Version: 0.1.8
Summary: CortexHub Python SDK - Policy-as-Code for AI Agents
Project-URL: Homepage, https://cortexhub.ai
Project-URL: Documentation, https://docs.cortexhub.ai
Project-URL: Repository, https://github.com/cortexhub/sdks
Project-URL: Issues, https://github.com/cortexhub/sdks/issues
Author-email: CortexHub <hello@cortexhub.ai>
License: MIT
License-File: LICENSE
Keywords: agents,ai,authorization,cedar,governance,policy
Classifier: Development Status :: 4 - Beta
Classifier: Intended Audience :: Developers
Classifier: License :: OSI Approved :: MIT License
Classifier: Programming Language :: Python :: 3
Classifier: Programming Language :: Python :: 3.10
Classifier: Programming Language :: Python :: 3.11
Classifier: Programming Language :: Python :: 3.12
Classifier: Programming Language :: Python :: 3.13
Classifier: Topic :: Software Development :: Libraries :: Python Modules
Requires-Python: <3.14,>=3.10
Requires-Dist: cedarpy>=4.0.0
Requires-Dist: detect-secrets>=1.5.0
Requires-Dist: httpx>=0.28.0
Requires-Dist: opentelemetry-api>=1.20.0
Requires-Dist: opentelemetry-exporter-otlp-proto-http>=1.20.0
Requires-Dist: opentelemetry-sdk>=1.20.0
Requires-Dist: pip>=23.0
Requires-Dist: presidio-analyzer>=2.2.360
Requires-Dist: presidio-anonymizer>=2.2.360
Requires-Dist: pydantic>=2.9.0
Requires-Dist: python-dotenv>=1.0.0
Requires-Dist: structlog>=24.4.0
Provides-Extra: all
Requires-Dist: anthropic>=0.40.0; extra == 'all'
Requires-Dist: claude-agent-sdk>=0.0.1; extra == 'all'
Requires-Dist: crewai>=0.50.0; extra == 'all'
Requires-Dist: langchain-core>=0.2.0; extra == 'all'
Requires-Dist: langchain-openai>=0.1.0; extra == 'all'
Requires-Dist: langgraph>=0.2.0; extra == 'all'
Requires-Dist: litellm>=1.81.5; extra == 'all'
Requires-Dist: openai-agents>=0.0.3; extra == 'all'
Provides-Extra: claude-agents
Requires-Dist: anthropic>=0.40.0; extra == 'claude-agents'
Requires-Dist: claude-agent-sdk>=0.0.1; extra == 'claude-agents'
Provides-Extra: crewai
Requires-Dist: crewai>=0.50.0; extra == 'crewai'
Requires-Dist: litellm>=1.81.5; extra == 'crewai'
Provides-Extra: dev
Requires-Dist: mypy>=1.10.0; extra == 'dev'
Requires-Dist: pytest-asyncio>=0.24.0; extra == 'dev'
Requires-Dist: pytest-cov>=5.0.0; extra == 'dev'
Requires-Dist: pytest>=8.0.0; extra == 'dev'
Requires-Dist: ruff>=0.4.0; extra == 'dev'
Provides-Extra: langgraph
Requires-Dist: langchain-core>=0.2.0; extra == 'langgraph'
Requires-Dist: langchain-openai>=0.1.0; extra == 'langgraph'
Requires-Dist: langgraph>=0.2.0; extra == 'langgraph'
Provides-Extra: openai-agents
Requires-Dist: openai-agents>=0.0.3; extra == 'openai-agents'
